{
  "id": "ukr_5_0003",
  "subject": "ukrainian",
  "theme": "Лексикологія: синоніми",
  "skills": [
    "Аналітичне мислення"
  ],
  "body": {
    "text": "Оберіть три синоніми до слова «гарний»."
  },
  "variants": {
    "multiple_select": {
      "options": [
        "красивий",
        "вродливий",
        "прекрасний",
        "огидний",
        "потворний",
        "недолугий",
        "похмурий"
      ],
      "correct": [
        0,
        1,
        2
      ],
      "shuffle": true,
      "k": 3
    }
  },
  "explanation": ""
}