{
  "id": "math_2_0012",
  "subject": "math",
  "theme": "Дроби та десяткові",
  "skills": [
    "Числа, відсотки та вирази"
  ],
  "body": {
    "text": "Установіть відповідність між дробом і його десятковим записом."
  },
  "variants": {
    "match": {
      "left": [
        "\\(\\tfrac{1}{4}\\)",
        "\\(\\tfrac{2}{5}\\)",
        "\\(\\tfrac{7}{8}\\)",
        "\\(\\tfrac{5}{2}\\)"
      ],
      "options": [
        "0.25",
        "0.4",
        "0.875",
        "2.5"
      ],
      "correctMap": {
        "0": 0,
        "1": 1,
        "2": 2,
        "3": 3
      }
    }
  },
  "explanation": "Стандарти перетворень дробів."
}