{
  "id": "history_4_0012",
  "subject": "history",
  "theme": "Міжнародні угоди",
  "skills": [
    "Історична хронологія"
  ],
  "body": {
    "text": "Розташуйте за часом міжнародні угоди з впливом на Україну."
  },
  "variants": {
    "order": {
      "items": [
        "Люблінська унія",
        "Андрусівське перемир’я",
        "Перший поділ Речі Посполитої",
        "Остаточна ліквідація Запорозької Січі"
      ],
      "shuffle": true
    }
  },
  "explanation": "1569 → 1667 → 1772 → 1775."
}